<?xml version="1.0" encoding="UTF-8"?>
<objects serializationModel="Studio.02.02.00">
	<object class="AudioFile" id="{a0bc5ce8-c827-4866-8d4a-a51753d28b7c}">
		<property name="assetPath">
			<value>Bobo5.wav</value>
		</property>
		<property name="frequencyInKHz">
			<value>48</value>
		</property>
		<property name="channelCount">
			<value>2</value>
		</property>
		<property name="length">
			<value>3.6649791666666665</value>
		</property>
		<relationship name="masterAssetFolder">
			<destination>{ba190cdf-7dab-47c7-9ca8-c27a40d9e2fe}</destination>
		</relationship>
	</object>
</objects>
